[
    {
        "item_name": "Dhaniya Paneer Tikka",
        "price": "675",
        "description": "Apricot, almond slivers, corn chat, pickled mango dip"
    },
    {
        "item_name": "Chicken or Paneer Kathi Roll",
        "price": "750",
        "description": "Grilled chicken tikka or paneer tikka, green apple relish, mint chutney"
    },
    {
        "item_name": "Pav Bhaji",
        "price": "685",
        "description": "Classic Bombay street food, spicy mashed potatoes & vegetable mixture,"
    },
    {
        "item_name": "Kheema Ghotala",
        "price": "785",
        "description": "Bombay street food classic, spiced minced lamb, egg,"
    },
    {
        "item_name": "Goan Pomfret Curry",
        "price": "1325",
        "description": "Mildly spiced coconut curry flavoured with Garcinia indica rind,"
    },
    {
        "item_name": "Vegetable Club Sandwich",
        "price": "685",
        "description": "Russian salad, tomato, cheese, iceberg lettuce"
    },
    {
        "item_name": "Vegetarian Panini sandwich",
        "price": "685",
        "description": "Herbed mushroom, grilled pimentos, avocado, provolone cheese,"
    },
    {
        "item_name": "Classic Club Sandwich",
        "price": "685",
        "description": "Chicken slices, fried egg, ham, cheese, tomato, iceberg lettuce"
    }
]